{
    "1": {
        "text": "Вопрос 1",
        "answers": {
            "11": {
                "text": "Ответ 1",
                "correct": true
            },
            "12": {
                "text": "Ответ 2",
                "correct": false
            },
            "13": {
                "text": "Ответ 3",
                "correct": false
            },
            "14": {
                "text": "Ответ 4",
                "correct": false
            },
            "15": {
                "text": "Ответ 5",
                "correct": false
            },
            "16": {
                "text": "Ответ 6",
                "correct": false
            }
        }
    },
    "2": {
        "text": "Вопрос 2",
        "answers": {
            "21": {
                "text": "Ответ 1",
                "correct": true
            },
            "22": {
                "text": "Ответ 2",
                "correct": false
            },
            "23": {
                "text": "Ответ 3",
                "correct": false
            },
            "24": {
                "text": "Ответ 4",
                "correct": false
            },
            "25": {
                "text": "Ответ 5",
                "correct": false
            },
            "26": {
                "text": "Ответ 6",
                "correct": false
            }
        }
    },
    "3": {
        "text": "Вопрос 3",
        "answers": {
            "31": {
                "text": "Ответ 1",
                "correct": true
            },
            "32": {
                "text": "Ответ 2",
                "correct": false
            },
            "33": {
                "text": "Ответ 3",
                "correct": false
            },
            "34": {
                "text": "Ответ 4",
                "correct": false
            },
            "35": {
                "text": "Ответ 5",
                "correct": false
            },
            "36": {
                "text": "Ответ 6",
                "correct": false
            }
        }
    },
    "4": {
        "text": "Вопрос 4",
        "answers": {
            "41": {
                "text": "Ответ 1",
                "correct": true
            },
            "42": {
                "text": "Ответ 2",
                "correct": false
            },
            "43": {
                "text": "Ответ 3",
                "correct": false
            },
            "44": {
                "text": "Ответ 4",
                "correct": false
            },
            "45": {
                "text": "Ответ 5",
                "correct": false
            },
            "46": {
                "text": "Ответ 6",
                "correct": false
            }
        }
    },
    "5": {
        "text": "Вопрос 5",
        "answers": {
            "51": {
                "text": "Ответ 1",
                "correct": true
            },
            "52": {
                "text": "Ответ 2",
                "correct": false
            },
            "53": {
                "text": "Ответ 3",
                "correct": false
            },
            "54": {
                "text": "Ответ 4",
                "correct": false
            },
            "55": {
                "text": "Ответ 5",
                "correct": false
            },
            "56": {
                "text": "Ответ 6",
                "correct": false
            }
        }
    },
    "6": {
        "text": "Вопрос 6",
        "answers": {
            "61": {
                "text": "Ответ 1",
                "correct": true
            },
            "62": {
                "text": "Ответ 2",
                "correct": false
            },
            "63": {
                "text": "Ответ 3",
                "correct": false
            },
            "64": {
                "text": "Ответ 4",
                "correct": false
            },
            "65": {
                "text": "Ответ 5",
                "correct": false
            },
            "66": {
                "text": "Ответ 6",
                "correct": false
            }
        }
    }
}